pmpyro/__init__.py
pmpyro/inference.py
pmpyro/model.py
pmpyro/plots.py
pmpyro/tensor_ops.py
pmpyro/tests.py
pmpyro/utils.py
pm_pyro-0.3.3.dist-info/LICENSE
pm_pyro-0.3.3.dist-info/METADATA
pm_pyro-0.3.3.dist-info/WHEEL
pm_pyro-0.3.3.dist-info/top_level.txt
pm_pyro-0.3.3.dist-info/RECORD
