Metadata-Version: 2.1
Name: pm-pyro
Version: 0.3.3
Summary: A PyMC3-like Interface for Pyro Stochastic Functions
Home-page: https://github.com/suriyadeepan/pm-pyro
Author: Suriyadeepan Ramamoorthy
License: GNU Affero General Public License v3 or later (AGPLv3+)
Platform: UNKNOWN
Requires-Python: >=3.5
Requires-Dist: arviz
Requires-Dist: pymc3
Requires-Dist: pyro-ppl
